CMakeLists.txt
LICENSE
MANIFEST.in
README.md
setup.cfg
setup.py
cmake_modules/GitUtils.cmake
fpie/__init__.py
fpie/args.py
fpie/cli.py
fpie/gui.py
fpie/io.py
fpie/np_solver.py
fpie/numba_solver.py
fpie/process.py
fpie/taichi_solver.py
fpie.egg-info/PKG-INFO
fpie.egg-info/SOURCES.txt
fpie.egg-info/dependency_links.txt
fpie.egg-info/entry_points.txt
fpie.egg-info/not-zip-safe
fpie.egg-info/requires.txt
fpie.egg-info/top_level.txt
fpie/core/base_solver.h
fpie/core/cuda/CMakeLists.txt
fpie/core/cuda/equ.cu
fpie/core/cuda/grid.cu
fpie/core/cuda/solver.cc
fpie/core/cuda/solver.h
fpie/core/cuda/utils.cu
fpie/core/cuda/utils.h
fpie/core/gcc/CMakeLists.txt
fpie/core/gcc/equ.cc
fpie/core/gcc/grid.cc
fpie/core/gcc/solver.cc
fpie/core/gcc/solver.h
fpie/core/mpi/CMakeLists.txt
fpie/core/mpi/equ.cc
fpie/core/mpi/grid.cc
fpie/core/mpi/solver.cc
fpie/core/mpi/solver.h
fpie/core/openmp/CMakeLists.txt
fpie/core/openmp/equ.cc
fpie/core/openmp/grid.cc
fpie/core/openmp/solver.cc
fpie/core/openmp/solver.h