Metadata-Version: 2.1
Name: fpie
Version: 0.2.3
Summary: A fast poisson image editing algorithm implementation.
Home-page: https://github.com/Trinkle23897/Fast-Poisson-Image-Editing
Author: Jiayi Weng
Author-email: trinkle23897@gmail.com
License: MIT
Platform: UNKNOWN
Classifier: Development Status :: 3 - Alpha
Classifier: Intended Audience :: Science/Research
Classifier: Topic :: Software Development :: Libraries :: Python Modules
Classifier: License :: OSI Approved :: MIT License
Classifier: Programming Language :: Python :: 3.6
Classifier: Programming Language :: Python :: 3.7
Classifier: Programming Language :: Python :: 3.8
Classifier: Programming Language :: Python :: 3.9
Provides-Extra: dev
Provides-Extra: mpi
License-File: LICENSE
